{
  "actions": [
    {
      "acted_at": "2011-06-22", 
      "references": [
        {
          "reference": "CR S4018-4019", 
          "type": "consideration"
        }, 
        {
          "reference": "CR S4018", 
          "type": "text"
        }
      ], 
      "text": "Amendment SA 504 proposed by Senator Cornyn.", 
      "type": "action"
    }, 
    {
      "acted_at": "2011-06-23", 
      "references": [
        {
          "reference": "CR S4046", 
          "type": "consideration"
        }
      ], 
      "text": "Considered by Senate.", 
      "type": "action"
    }, 
    {
      "acted_at": "2011-06-28", 
      "references": [
        {
          "reference": "CR S4145", 
          "type": "consideration"
        }
      ], 
      "text": "Considered by Senate.", 
      "type": "action"
    }, 
    {
      "acted_at": "2011-06-28", 
      "references": [
        {
          "reference": "CR S4147", 
          "type": "consideration"
        }
      ], 
      "text": "Proposed amendment SA 504 withdrawn in Senate.", 
      "type": "withdrawn"
    }
  ], 
  "amendment_id": "samdt504-112", 
  "amendment_type": "samdt", 
  "amends_amendment": null, 
  "amends_bill": {
    "bill_id": "s679-112", 
    "bill_type": "s", 
    "congress": 112, 
    "number": 679
  }, 
  "amends_treaty": null, 
  "chamber": "s", 
  "congress": "112", 
  "description": null, 
  "introduced_at": "2011-06-22", 
  "number": 504, 
  "proposed_at": "2011-06-22", 
  "purpose": "To strike the provisions relating to the Comptroller of the Army, the Comptroller of the Navy, and the Comptroller of the Air Force.", 
  "sponsor": {
    "district": null, 
    "name": "Cornyn, John", 
    "state": "TX", 
    "thomas_id": "01692", 
    "title": "Sen", 
    "type": "person"
  }, 
  "status": "withdrawn", 
  "status_at": "2011-06-28", 
  "updated_at": "2013-07-19T20:10:27-04:00"
}